{
  "host": "127.0.0.1",
  "port": 24789,
  "baseUrl": "http://127.0.0.1:24789",
  "session": {
    "cookieName": "nexus_fd_session",
    "ttlSeconds": 604800,
    "storePath": "/Users/tyler/nexus/home/projects/nexus/.hosted-demo/frontdoor-sessions.db"
  },
  "runtimeToken": {
    "issuer": "https://frontdoor.demo.nexus",
    "audience": "control-plane",
    "secret": "frontdoor-demo-shared-secret-2026-02-23",
    "activeKid": "v1",
    "keys": {
      "v1": "frontdoor-demo-shared-secret-2026-02-23"
    },
    "ttlSeconds": 600,
    "refreshTtlSeconds": 2592000
  },
  "security": {
    "rateLimits": {
      "loginAttempts": {
        "windowSeconds": 60,
        "maxAttempts": 30,
        "blockSeconds": 60
      },
      "loginFailures": {
        "windowSeconds": 900,
        "maxAttempts": 8,
        "blockSeconds": 900
      },
      "tokenEndpoints": {
        "windowSeconds": 60,
        "maxAttempts": 120,
        "blockSeconds": 60
      },
      "proxyRequests": {
        "windowSeconds": 60,
        "maxAttempts": 1000,
        "blockSeconds": 30
      }
    }
  },
  "tenants": {
    "tenant-dev": {
      "runtimeUrl": "http://127.0.0.1:28789",
      "runtimePublicBaseUrl": "https://butter-lung-ideas-glenn.trycloudflare.com"
    }
  },
  "users": [
    {
      "id": "user-owner",
      "username": "owner",
      "passwordHash": "scrypt-sha256-v1$Q2Pk_UGb_MWMHj_iNKt5mw$9LMyZ85W_i5G5yK-q22uow7_jL3ule5gyrXxlXE3C0g",
      "tenantId": "tenant-dev",
      "entityId": "entity-owner",
      "displayName": "Owner",
      "email": "owner@example.com",
      "roles": [
        "operator"
      ],
      "scopes": [
        "*"
      ]
    }
  ],
  "oidc": {
    "enabled": false,
    "providers": {},
    "mappings": []
  }
}
